stater/__init__.py
stater-0.0.1.dist-info/LICENSE
stater-0.0.1.dist-info/METADATA
stater-0.0.1.dist-info/WHEEL
stater-0.0.1.dist-info/top_level.txt
stater-0.0.1.dist-info/RECORD
