Metadata-Version: 2.1
Name: stater
Version: 0.0.1
Summary: A wrapper for the Stater-API
Home-page: https://github.com/mithem/PyServer
Author: mithem
Author-email: miguel.themann@gmail.com
License: UNKNOWN
Platform: UNKNOWN
Classifier: Programming Language :: Python :: 3
Classifier: License :: OSI Approved :: MIT License
Classifier: Operating System :: OS Independent
Requires-Python: >=3.6
